c2fj/__init__.py
c2fj/c2fj_main.py
c2fj/compilation_files/Makefile_single_c_generic
c2fj/compilation_files/c2fj_init.c
c2fj/compilation_files/include/c2fj_syscall.h
c2fj/compilation_files/linker_script.ld
c2fj/compilation_files/riscvlib.fj
c2fj/riscv_instructions.py
c2fj/riscv_to_fj.py
c2fj-1.0.0.dist-info/LICENSE
c2fj-1.0.0.dist-info/METADATA
c2fj-1.0.0.dist-info/WHEEL
c2fj-1.0.0.dist-info/entry_points.txt
c2fj-1.0.0.dist-info/RECORD
