Metadata-Version: 2.3
Name: c2fj
Version: 1.0.0
Summary: A C to flipjump compiler
License: BSD-2-Clause-Simplified
Keywords: esolang,oisc,assembly,compiler
Author: Tom Herman
Author-email: flipjumpproject@gmail.com
Requires-Python: >=3.8.1,<4.0.0
Classifier: Intended Audience :: Developers
Classifier: Intended Audience :: Education
Classifier: Intended Audience :: Science/Research
Classifier: License :: Other/Proprietary License
Classifier: Operating System :: OS Independent
Classifier: Programming Language :: C
Classifier: Programming Language :: Other
Classifier: Programming Language :: Python :: 3
Classifier: Programming Language :: Python :: 3.9
Classifier: Programming Language :: Python :: 3.10
Classifier: Programming Language :: Python :: 3.11
Classifier: Programming Language :: Python :: 3.12
Classifier: Programming Language :: Python :: 3.13
Classifier: Programming Language :: Python :: 3.8
Classifier: Topic :: Education
Classifier: Topic :: Software Development :: Assemblers
Classifier: Topic :: Software Development :: Compilers
Classifier: Topic :: Software Development :: Debuggers
Classifier: Topic :: Software Development :: Interpreters
Classifier: Topic :: Software Development :: Libraries
Provides-Extra: tests
Requires-Dist: flipjump (>=1.3.0)
Requires-Dist: pyelftools (>=0.31)
Requires-Dist: pytest (>=7.4.0,<8.0.0) ; extra == "tests"
Requires-Dist: pytest-xdist (>=3.3.1,<4.0.0) ; extra == "tests"
Project-URL: Homepage, https://esolangs.org/wiki/FlipJump
Project-URL: Repository, https://github.com/tomhea/c2fj
